graphesn/__init__.py
graphesn/data.py
graphesn/dataset.py
graphesn/matrix.py
graphesn/readout.py
graphesn/reservoir.py
graphesn/sparse_reservoir.py
graphesn/util.py
graphesn-0.2.17.dist-info/LICENSE
graphesn-0.2.17.dist-info/METADATA
graphesn-0.2.17.dist-info/WHEEL
graphesn-0.2.17.dist-info/top_level.txt
graphesn-0.2.17.dist-info/RECORD
