Metadata-Version: 2.1
Name: graphesn
Version: 0.2.17
Summary: Python implementation of Deep Graph Echo State Networks
Home-page: https://github.com/dtortorella/graph-esn
Author: Domenico Tortorella, Danilo Numeroso, Alessio Gravina
Author-email: d.tortorella@phd.unipi.it, d.numeroso@phd.unipi.it, a.gravina@phd.unipi.it
Project-URL: Bug Tracker, https://github.com/dtortorella/graph-esn
Classifier: Programming Language :: Python :: 3
Classifier: License :: OSI Approved :: MIT License
Classifier: Operating System :: OS Independent
Requires-Python: >=3.8
License-File: LICENSE
